loguru_json/__init__.py
loguru_json/format.py
loguru_json/json_encoder/__init__.py
loguru_json/monkey.py
json_loguru-0.1.1.dist-info/METADATA
json_loguru-0.1.1.dist-info/WHEEL
json_loguru-0.1.1.dist-info/RECORD
